README.rst
setup.py
WunderWeather/__init__.py
WunderWeather/date.py
WunderWeather/forecast.py
WunderWeather/test.py
WunderWeather/test_responses.py
WunderWeather/today.py
WunderWeather/weather.py
WunderWeather/weather_base.py
WunderWeather.egg-info/PKG-INFO
WunderWeather.egg-info/SOURCES.txt
WunderWeather.egg-info/dependency_links.txt
WunderWeather.egg-info/requires.txt
WunderWeather.egg-info/top_level.txt