Metadata-Version: 1.1
Name: WunderWeather
Version: 1.1.0
Summary: Wrapper for Weather Underground API
Home-page: http://wunderweather.readthedocs.io/en/latest/
Author: Tyler Santos
Author-email: 1tsantos7+wunderweather@gmail.com
License: UNKNOWN
Download-URL: https://github.com/T-Santos/WunderWeather
Keywords: weather,wunderground
Platform: UNKNOWN
Classifier: Development Status :: 3 - Alpha
Classifier: Intended Audience :: Developers
Classifier: Programming Language :: Python :: 3.5
